Metadata-Version: 2.1
Name: ansys-tools-protos-generator
Version: 0.1.0
Summary: PyAnsys Protos Generator Packaging Tool
Home-page: https://github.com/pyansys/pyansys-protos-generator/
Author: ANSYS, Inc.
Maintainer: Alexander Kaszynski
Maintainer-email: alexander.kaszynski@ansys.com
License: MIT
Platform: UNKNOWN
Classifier: Development Status :: 4 - Beta
Classifier: Programming Language :: Python :: 3
Classifier: License :: OSI Approved :: MIT License
Classifier: Operating System :: OS Independent
Requires-Python: >=3.5
